minty/__init__.py
minty/date_calculation.py
minty/entity.py
minty/exceptions.py
minty/middleware.py
minty/object.py
minty/py.typed
minty/repository.py
minty/validation.py
minty/config/__init__.py
minty/config/parser/__init__.py
minty/config/parser/apache.py
minty/config/parser/base.py
minty/config/parser/json_parser.py
minty/config/store/__init__.py
minty/config/store/base.py
minty/config/store/filestore.py
minty/config/store/redis.py
minty/cqrs/__init__.py
minty/cqrs/events.py
minty/cqrs/test.py
minty/infrastructure/__init__.py
minty/infrastructure/mime_utils.py
minty/logging/__init__.py
minty/logging/mdc.py
minty-3.1.0.dist-info/METADATA
minty-3.1.0.dist-info/WHEEL
minty-3.1.0.dist-info/top_level.txt
minty-3.1.0.dist-info/RECORD
