Metadata-Version: 2.1
Name: minty
Version: 3.1.0
Summary: Minty Command and Query based on DDD
Home-page: https://gitlab.com/minty-python/minty
Author: Michiel Ootjers
Author-email: michiel@mintlab.nl
License: EUPL license
Keywords: minty
Classifier: Development Status :: 5 - Production/Stable
Classifier: Intended Audience :: Developers
Classifier: License :: OSI Approved :: European Union Public Licence 1.2 (EUPL 1.2)
Classifier: Natural Language :: English
Classifier: Programming Language :: Python :: 3.9
Requires-Dist: pytz >=2021.3
Requires-Dist: amqpstorm
Requires-Dist: apacheconfig ~=0.3
Requires-Dist: file-magic
Requires-Dist: holidays ==0.16
Requires-Dist: jsonpointer
Requires-Dist: jsonschema
Requires-Dist: python-statsd
Requires-Dist: redis
Requires-Dist: pydantic <2.0,>=1.0
